{
  "project_info": {
    "project_number": "356499883164",
    "firebase_url": "https://practicepresentation-ba803-default-rtdb.firebaseio.com",
    "project_id": "practicepresentation-ba803",
    "storage_bucket": "practicepresentation-ba803.appspot.com"
  },
  "client": [
    {
      "client_info": {
        "mobilesdk_app_id": "1:356499883164:android:725250d56a6b761f871959",
        "android_client_info": {
          "package_name": "com.mycompany.pricecardpresentation"
        }
      },
      "oauth_client": [],
      "api_key": [
        {
          "current_key": "AIzaSyBbd6ISt1VLuqhDfr9AGvFHvCOwTlkGYiU"
        }
      ],
      "services": {
        "appinvite_service": {
          "other_platform_oauth_client": []
        }
      }
    }
  ],
  "configuration_version": "1"
}